Spruce_logging-0.1.3-py2.7-nspkg.pth
spruce/logging/_core.py
spruce/logging/_pprint.py
spruce/logging/__init__.py
Spruce_logging-0.1.3.dist-info/top_level.txt
Spruce_logging-0.1.3.dist-info/RECORD
Spruce_logging-0.1.3.dist-info/pydist.json
Spruce_logging-0.1.3.dist-info/WHEEL
Spruce_logging-0.1.3.dist-info/namespace_packages.txt
Spruce_logging-0.1.3.dist-info/METADATA
Spruce_logging-0.1.3.dist-info/entry_points.txt
Spruce_logging-0.1.3.dist-info/DESCRIPTION.rst
