Metadata-Version: 2.0
Name: Spruce-logging
Version: 0.1.3
Summary: Logging
Home-page: UNKNOWN
Author: Ivan D Vasin
Author-email: nisavid@gmail.com
License: GNU LESSER GENERAL PUBLIC LICENSE
Requires-Dist: spruce-pprint
